{
    "article_title": "New analyst forecast says X's advertising revenue is on the upswing, driven partly by 'fear'",
    "article_source": "Business Insider",
    "article_url": "https://www.businessinsider.com/elon-musk-x-advertising-revenue-on-upswing-analys-estimates-2025-3",
    "article_date": "2025-03-26T18:41:37Z",
    "summary": "The article discusses a new analyst forecast indicating that X's advertising revenue is increasing, partly attributed to a sense of 'fear' motivating businesses to spend on advertising.",
    "summary_generated_at": "2025-03-26T23:17:05.270004"
}